MANIFEST.in
README.rst
setup.py
.src/jmb.core/.src/jmb.sphinx/build/lib.linux-x86_64-2.7/jmb/sphinx/themes/jumbo/jquery.js
.src/jmb.core/.src/jmb.sphinx/build/lib.linux-x86_64-2.7/jmb/sphinx/themes/jumbo/layout.html
.src/jmb.core/.src/jmb.sphinx/build/lib.linux-x86_64-2.7/jmb/sphinx/themes/jumbo/navbar.html
.src/jmb.core/.src/jmb.sphinx/build/lib.linux-x86_64-2.7/jmb/sphinx/themes/jumbo/static/bootstrap.css
.src/jmb.core/.src/jmb.sphinx/build/lib.linux-x86_64-2.7/jmb/sphinx/themes/jumbo/static/bootstrap.js
.src/jmb.core/.src/jmb.sphinx/build/lib.linux-x86_64-2.7/jmb/sphinx/themes/jumbo/static/jquery.js
.src/jmb.core/.src/jmb.sphinx/build/lib.linux-x86_64-2.7/jmb/sphinx/themes/thunder/static/logo-thunder.png
.src/jmb.core/.src/jmb.sphinx/jmb/sphinx/themes/jumbo/jquery.js
.src/jmb.core/.src/jmb.sphinx/jmb/sphinx/themes/jumbo/layout.html
.src/jmb.core/.src/jmb.sphinx/jmb/sphinx/themes/jumbo/navbar.html
.src/jmb.core/.src/jmb.sphinx/jmb/sphinx/themes/jumbo/static/bootstrap.css
.src/jmb.core/.src/jmb.sphinx/jmb/sphinx/themes/jumbo/static/bootstrap.js
.src/jmb.core/.src/jmb.sphinx/jmb/sphinx/themes/jumbo/static/jquery.js
.src/jmb.core/.src/jmb.sphinx/jmb/sphinx/themes/thunder/static/logo-thunder.png
.src/jmb.core/build/lib.linux-x86_64-2.7/jmb/core/locale/en/LC_MESSAGES/django.po
.src/jmb.core/build/lib.linux-x86_64-2.7/jmb/core/locale/en/LC_MESSAGES/djangojs.po
.src/jmb.core/build/lib.linux-x86_64-2.7/jmb/core/locale/it/LC_MESSAGES/django.po
.src/jmb.core/build/lib.linux-x86_64-2.7/jmb/core/locale/it/LC_MESSAGES/djangojs.po
.src/jmb.core/build/lib.linux-x86_64-2.7/jmb/core/static/bootstrap/css/bootstrap-responsive.min.css
.src/jmb.core/build/lib.linux-x86_64-2.7/jmb/core/static/bootstrap/css/bootstrap.css
.src/jmb.core/build/lib.linux-x86_64-2.7/jmb/core/static/bootstrap/css/bootstrap.min.css
.src/jmb.core/build/lib.linux-x86_64-2.7/jmb/core/static/bootstrap/img/glyphicons-halflings-white.png
jmb.jadmin.egg-info/PKG-INFO
jmb.jadmin.egg-info/SOURCES.txt
jmb.jadmin.egg-info/dependency_links.txt
jmb.jadmin.egg-info/namespace_packages.txt
jmb.jadmin.egg-info/not-zip-safe
jmb.jadmin.egg-info/requires.txt
jmb.jadmin.egg-info/top_level.txt
