Metadata-Version: 1.1
Name: jmb.jadmin
Version: 0.8.1
Summary: jumbo admin
Home-page: https://bitbucket.org/jumboteam/jmb.jadmin
Author: ThunderSystems
Author-email: dev@thundersystems.it
License: UNKNOWN
Platform: any
Classifier: Operating System :: OS Independent
Classifier: Programming Language :: Python
Classifier: Topic :: Internet :: WWW/HTTP :: Dynamic Content
Classifier: Framework :: Django
